jsoniq/__init__.py
jsoniq/sequence.py
jsoniq/session.py
jsoniq/jars/rumbledb-2.0.8.jar
jsoniq-2.0.9.dist-info/licenses/LICENSE
jsoniqmagic/__init__.py
jsoniqmagic/magic.py
jsoniq-2.0.9.dist-info/METADATA
jsoniq-2.0.9.dist-info/WHEEL
jsoniq-2.0.9.dist-info/top_level.txt
jsoniq-2.0.9.dist-info/RECORD
