Metadata-Version: 2.4
Name: jsoniq
Version: 2.0.9
Summary: Python edition of RumbleDB, a JSONiq engine
Author: Abishek Ramdas
Author-email: Ghislain Fourny <ghislain.fourny@inf.ethz.ch>
License:                                  Apache License
Project-URL: Homepage, https://rumbledb.org
Project-URL: Documentation, https://rumble.readthedocs.io/en/latest/
Project-URL: Repository, https://github.com/RumbleDB/python-jsoniq.git
Project-URL: Bug Tracker, https://github.com/RumbleDB/python-jsoniq/issues
Keywords: jsoniq,spark,apache-spark,dataframe,heterogeneous,json,query
Classifier: Development Status :: 3 - Alpha
Classifier: Intended Audience :: Developers
Classifier: Programming Language :: Python :: 3.11
Classifier: Programming Language :: Python :: 3.12
Classifier: Programming Language :: Python :: 3.13
Classifier: Typing :: Typed
Classifier: License :: OSI Approved :: Apache Software License
Requires-Python: >=3.11
License-File: LICENSE
Requires-Dist: pyspark==4.0.1
Requires-Dist: pandas>=2.2
Requires-Dist: delta-spark==4.0
Dynamic: license-file
